setup.py
GetTimeEasy/GetTimeEasy.py
GetTimeEasy/__init__.py
GetTimeEasy.egg-info/PKG-INFO
GetTimeEasy.egg-info/SOURCES.txt
GetTimeEasy.egg-info/dependency_links.txt
GetTimeEasy.egg-info/top_level.txt