Metadata-Version: 2.1
Name: GetTimeEasy
Version: 2.0.0
Summary: time and date library
Author: Luka
Author-email: app6onpython@gmail.com
License: MIT
Keywords: GetTimeEasy,gettimeeasy,Gettimeeasy,Get Time Easyget time easy,Get time easy,Get,get,Time,time,Easy,easy
Classifier: Programming Language :: Python :: 3.5
Classifier: Programming Language :: Python :: 3.6
Classifier: Programming Language :: Python :: 3.7
Classifier: Programming Language :: Python :: 3.8
Classifier: Programming Language :: Python :: 3.9
